debategpt/__init__.py
debategpt/inference/__init__.py
debategpt/inference/core.py
debategpt/training/__init__.py
debategpt/training/orchestrator.py
debategpt/training/reward.py
debategpt/training/trainer.py
debategpt-0.0.4.dist-info/LICENCE.txt
debategpt-0.0.4.dist-info/METADATA
debategpt-0.0.4.dist-info/WHEEL
debategpt-0.0.4.dist-info/dependency_links.txt
debategpt-0.0.4.dist-info/top_level.txt
debategpt-0.0.4.dist-info/RECORD
