Metadata-Version: 2.1
Name: debategpt
Version: 0.0.4
Summary: Train and use DebateGPT, a language model designed to simulate debates.
Author: paulbricman
Author-email: paulbricman@protonmail.com
License-File: LICENCE.txt
Requires-Dist: transformers
Requires-Dist: networkx
Requires-Dist: torch
Requires-Dist: sentencepiece
Requires-Dist: protobuf (==3.20.0)
Requires-Dist: scipy (==1.9.3)
